{
	"name": "SQL_Doorgangen_idas_urmshp",
	"properties": {
		"linkedServiceName": {
			"referenceName": "DOORGANGEN_PROD_SRV_SQL_00",
			"type": "LinkedServiceReference"
		},
		"annotations": [],
		"type": "AzureSqlTable",
		"schema": [
			{
				"name": "GHBRAN",
				"type": "decimal",
				"precision": 2,
				"scale": 0
			},
			{
				"name": "GHSDOC",
				"type": "decimal",
				"precision": 7,
				"scale": 0
			},
			{
				"name": "GHMONT",
				"type": "decimal",
				"precision": 4,
				"scale": 0
			},
			{
				"name": "GHDATE",
				"type": "char"
			},
			{
				"name": "GHBTIM",
				"type": "char"
			},
			{
				"name": "GHETIM",
				"type": "char"
			},
			{
				"name": "GHGMIN",
				"type": "decimal",
				"precision": 4,
				"scale": 0
			},
			{
				"name": "GHSTAT",
				"type": "varchar"
			},
			{
				"name": "GHBKLK",
				"type": "char"
			},
			{
				"name": "GHEKLK",
				"type": "char"
			}
		],
		"typeProperties": {
			"schema": "dbo",
			"table": "idas_urmshp"
		}
	},
	"type": "Microsoft.DataFactory/factories/datasets"
}